semiq_ml/__init__.py
semiq_ml/baseline_model.py
semiq_ml/image.py
semiq_ml/trial_suggest.py
semiq_ml/tuning.py
semiq_ml-0.4.9.dist-info/licenses/LICENSE
semiq_ml-0.4.9.dist-info/METADATA
semiq_ml-0.4.9.dist-info/WHEEL
semiq_ml-0.4.9.dist-info/top_level.txt
semiq_ml-0.4.9.dist-info/RECORD
