Metadata-Version: 2.4
Name: semiq-ml
Version: 0.4.9
Summary: A collection of reusable machine learning pipeline helpers
Author-email: Malfino Willianz <willianz@pm.me>
License: MIT
Project-URL: Homepage, https://github.com/semiqolonn/semiq-ml
Project-URL: Bug Tracker, https://github.com/semiqolonn/semiq-ml/issues
Classifier: Programming Language :: Python :: 3
Classifier: Programming Language :: Python :: 3.12
Classifier: License :: OSI Approved :: MIT License
Classifier: Operating System :: OS Independent
Requires-Python: >=3.12
License-File: LICENSE
Requires-Dist: numpy
Requires-Dist: pandas
Requires-Dist: scikit-learn
Requires-Dist: matplotlib
Requires-Dist: seaborn
Requires-Dist: lightgbm
Requires-Dist: xgboost
Requires-Dist: catboost
Requires-Dist: optuna
Requires-Dist: Pillow
Requires-Dist: tqdm
Dynamic: license-file
